{"name":"grabbag","counts":{"unstable":7,"stable":45,"unmarked":143},"submodules":[{"name":"iter","counts":{"unstable":7,"stable":45,"unmarked":142},"submodules":[{"name":"accumulate","counts":{"unstable":0,"stable":1,"unmarked":6},"submodules":[]},{"name":"cartesian_product","counts":{"unstable":0,"stable":3,"unmarked":4},"submodules":[]},{"name":"clone_each","counts":{"unstable":1,"stable":4,"unmarked":6},"submodules":[]},{"name":"fold","counts":{"unstable":0,"stable":0,"unmarked":6},"submodules":[]},{"name":"group_by","counts":{"unstable":0,"stable":2,"unmarked":6},"submodules":[]},{"name":"indexed","counts":{"unstable":2,"stable":7,"unmarked":10},"submodules":[]},{"name":"intersperse","counts":{"unstable":1,"stable":3,"unmarked":4},"submodules":[]},{"name":"keep_some","counts":{"unstable":0,"stable":4,"unmarked":6},"submodules":[]},{"name":"pacing_walk","counts":{"unstable":0,"stable":3,"unmarked":6},"submodules":[]},{"name":"pad_tail_to","counts":{"unstable":1,"stable":2,"unmarked":6},"submodules":[]},{"name":"prelude","counts":{"unstable":0,"stable":0,"unmarked":1},"submodules":[]},{"name":"round_robin","counts":{"unstable":0,"stable":6,"unmarked":10},"submodules":[]},{"name":"skip_exactly","counts":{"unstable":0,"stable":0,"unmarked":3},"submodules":[]},{"name":"sorted","counts":{"unstable":0,"stable":0,"unmarked":4},"submodules":[]},{"name":"stride","counts":{"unstable":1,"stable":3,"unmarked":6},"submodules":[]},{"name":"take_exactly","counts":{"unstable":1,"stable":3,"unmarked":6},"submodules":[]},{"name":"tee","counts":{"unstable":0,"stable":1,"unmarked":5},"submodules":[]},{"name":"zip_longest","counts":{"unstable":0,"stable":3,"unmarked":6},"submodules":[]}]}]}